benchenas/__init__.py
benchenas/init_compute.py
benchenas/main.py
benchenas/read_best_acc.py
benchenas/tools.py
benchenas/algs/__init__.py
benchenas/algs/aecnn/__init__.py
benchenas/algs/aecnn/main.py
benchenas/algs/aecnn/utils.py
benchenas/algs/aecnn/genetic/__init__.py
benchenas/algs/aecnn/genetic/crossover_and_mutation.py
benchenas/algs/aecnn/genetic/evaluate.py
benchenas/algs/aecnn/genetic/global.ini
benchenas/algs/aecnn/genetic/population.py
benchenas/algs/aecnn/genetic/selection_operator.py
benchenas/algs/aecnn/genetic/statusupdatetool.py
benchenas/algs/aecnn/template/__init__.py
benchenas/algs/aecnn/template/model_template.py
benchenas/algs/cgp_cnn/__init__.py
benchenas/algs/cgp_cnn/cgp_config.py
benchenas/algs/cgp_cnn/main.py
benchenas/algs/cgp_cnn/utils.py
benchenas/algs/cgp_cnn/genetic/__init__.py
benchenas/algs/cgp_cnn/genetic/evaluate.py
benchenas/algs/cgp_cnn/genetic/global.ini
benchenas/algs/cgp_cnn/genetic/population.py
benchenas/algs/cgp_cnn/genetic/statusupdatetool.py
benchenas/algs/cgp_cnn/template/__init__.py
benchenas/algs/cgp_cnn/template/model_template.py
benchenas/algs/cnn_ga/__init__.py
benchenas/algs/cnn_ga/global.ini
benchenas/algs/cnn_ga/main.py
benchenas/algs/cnn_ga/utils.py
benchenas/algs/cnn_ga/genetic/__init__.py
benchenas/algs/cnn_ga/genetic/crossover_and_mutation.py
benchenas/algs/cnn_ga/genetic/evaluate.py
benchenas/algs/cnn_ga/genetic/population.py
benchenas/algs/cnn_ga/genetic/selection_operator.py
benchenas/algs/cnn_ga/genetic/statusupdatetool.py
benchenas/algs/cnn_ga/template/__init__.py
benchenas/algs/cnn_ga/template/model_template.py
benchenas/algs/genetic_CNN/__init__.py
benchenas/algs/genetic_CNN/main.py
benchenas/algs/genetic_CNN/utils.py
benchenas/algs/genetic_CNN/genetic/__init__.py
benchenas/algs/genetic_CNN/genetic/crossover_and_mutation.py
benchenas/algs/genetic_CNN/genetic/dag.py
benchenas/algs/genetic_CNN/genetic/evaluate.py
benchenas/algs/genetic_CNN/genetic/global.ini
benchENAS-1.2.0.dist-info/LICENSE
benchENAS-1.2.0.dist-info/METADATA
benchENAS-1.2.0.dist-info/WHEEL
benchENAS-1.2.0.dist-info/top_level.txt
benchENAS-1.2.0.dist-info/RECORD
