Metadata-Version: 2.1
Name: benchENAS
Version: 1.2.0
Summary: A benchmark platform for Evolutionary Neural Architecture Search
Home-page: https://github.com/benchenas/BenchENA
Author: benchenas
Author-email: benchenas99@gmail.com
License: UNKNOWN
Platform: UNKNOWN
Classifier: Programming Language :: Python :: 3
Classifier: License :: OSI Approved :: MIT License
Classifier: Operating System :: OS Independent
License-File: LICENSE
Requires-Dist: paramiko
Requires-Dist: numpy
Requires-Dist: multiprocess
Requires-Dist: torch (==1.6.0)
Requires-Dist: torchvision (==0.7.0)
Requires-Dist: redis
Requires-Dist: scipy
